autopaths/__init__.py
autopaths/auto_paths.py
autopaths/base_path.py
autopaths/common.py
autopaths/dir_path.py
autopaths/file_path.py
autopaths/file_permissions.py
autopaths/file_size.py
autopaths/tmp_path.py
autopaths-1.1.3.dist-info/LICENSE.txt
autopaths-1.1.3.dist-info/METADATA
autopaths-1.1.3.dist-info/WHEEL
autopaths-1.1.3.dist-info/top_level.txt
autopaths-1.1.3.dist-info/RECORD
