Metadata-Version: 2.1
Name: autopaths
Version: 1.1.3
Summary: autopaths is a python package for dealing with file paths and automation.
Home-page: http://github.com/xapple/autopaths/
Author: Lucas Sinclair
Author-email: lucas.sinclair@me.com
License: MIT
Platform: UNKNOWN
Requires-Dist: sh
